azure_functions_worker/__init__.py
azure_functions_worker/__main__.py
azure_functions_worker/constants.py
azure_functions_worker/dispatcher.py
azure_functions_worker/functions.py
azure_functions_worker/loader.py
azure_functions_worker/logging.py
azure_functions_worker/main.py
azure_functions_worker/testutils.py
azure_functions_worker/_thirdparty/__init__.py
azure_functions_worker/_thirdparty/aio_compat.py
azure_functions_worker/_thirdparty/typing_inspect.py
azure_functions_worker/bindings/__init__.py
azure_functions_worker/bindings/context.py
azure_functions_worker/bindings/datumdef.py
azure_functions_worker/bindings/generic.py
azure_functions_worker/bindings/meta.py
azure_functions_worker/bindings/out.py
azure_functions_worker/bindings/tracecontext.py
azure_functions_worker/protos/FunctionRpc_pb2.py
azure_functions_worker/protos/FunctionRpc_pb2_grpc.py
azure_functions_worker/protos/__init__.py
azure_functions_worker/protos/identity/ClaimsIdentityRpc_pb2.py
azure_functions_worker/protos/identity/ClaimsIdentityRpc_pb2_grpc.py
azure_functions_worker/protos/identity/__init__.py
azure_functions_worker/protos/shared/NullableTypes_pb2.py
azure_functions_worker/protos/shared/NullableTypes_pb2_grpc.py
azure_functions_worker/protos/shared/__init__.py
azure_functions_worker/utils/__init__.py
azure_functions_worker/utils/common.py
azure_functions_worker/utils/tracing.py
azure_functions_worker/utils/wrappers.py
azure_functions_worker-1.1.9.dist-info/LICENSE
azure_functions_worker-1.1.9.dist-info/METADATA
azure_functions_worker-1.1.9.dist-info/WHEEL
azure_functions_worker-1.1.9.dist-info/top_level.txt
azure_functions_worker-1.1.9.dist-info/RECORD
