Metadata-Version: 2.1
Name: azure-functions-worker
Version: 1.1.9
Summary: Python Language Worker for Azure Functions Host
Home-page: https://github.com/Azure/azure-functions-python-worker
Author: Microsoft Corp.
Author-email: azurefunctions@microsoft.com
License: MIT
Keywords: azure azurefunctions python
Platform: UNKNOWN
Classifier: Development Status :: 5 - Production/Stable
Classifier: License :: OSI Approved :: MIT License
Classifier: Intended Audience :: Developers
Classifier: Programming Language :: Python :: 3
Classifier: Programming Language :: Python :: 3.6
Classifier: Programming Language :: Python :: 3.7
Classifier: Programming Language :: Python :: 3.8
Classifier: Programming Language :: Python :: 3.9
Classifier: Operating System :: Microsoft :: Windows
Classifier: Operating System :: POSIX
Classifier: Operating System :: MacOS :: MacOS X
Classifier: Environment :: Web Environment
Provides-Extra: dev
